xtnote/__init__.py
xtnote/cli.py
xtnote-0.1.0.dist-info/licenses/LICENSE
xtnote-0.1.0.dist-info/METADATA
xtnote-0.1.0.dist-info/WHEEL
xtnote-0.1.0.dist-info/entry_points.txt
xtnote-0.1.0.dist-info/top_level.txt
xtnote-0.1.0.dist-info/RECORD
